hightop_sdk/__init__.py
hightop_sdk/api_client.py
hightop_sdk/api_response.py
hightop_sdk/configuration.py
hightop_sdk/exceptions.py
hightop_sdk/py.typed
hightop_sdk/rest.py
hightop_sdk/api/__init__.py
hightop_sdk/api/actions_api.py
hightop_sdk/api/agents_api.py
hightop_sdk/api/auth_api.py
hightop_sdk/api/legos_api.py
hightop_sdk/api/messages_api.py
hightop_sdk/api/user_api.py
hightop_sdk/api/wallet_api.py
hightop_sdk/models/__init__.py
hightop_sdk/models/action_create_response.py
hightop_sdk/models/action_create_response_action_inner.py
hightop_sdk/models/action_create_response_message.py
hightop_sdk/models/action_get.py
hightop_sdk/models/action_get_by_id_payload.py
hightop_sdk/models/action_get_by_wallet_address.py
hightop_sdk/models/action_get_response.py
hightop_sdk/models/action_response.py
hightop_sdk/models/action_status.py
hightop_sdk/models/action_type.py
hightop_sdk/models/agent_create.py
hightop_sdk/models/agent_get.py
hightop_sdk/models/agent_get_by_wallet_address.py
hightop_sdk/models/agent_public_response.py
hightop_sdk/models/agent_update.py
hightop_sdk/models/agent_user_response.py
hightop_sdk/models/api_actions_agent_batch_post401_response.py
hightop_sdk/models/api_actions_agent_batch_post_request.py
hightop_sdk/models/api_actions_agent_batch_post_request_actions_inner.py
hightop_sdk/models/api_actions_agent_batch_post_request_message.py
hightop_sdk/models/api_actions_agent_deposit_post_request.py
hightop_sdk/models/api_actions_agent_end_conversation_post_request.py
hightop_sdk/models/api_actions_agent_rebalance_post_request.py
hightop_sdk/models/api_actions_agent_swap_post_request.py
hightop_sdk/models/api_actions_agent_transfer_post_request.py
hightop_sdk/models/api_actions_agent_unwrap_eth_post_request.py
hightop_sdk/models/api_actions_agent_withdraw_post_request.py
hightop_sdk/models/api_actions_agent_wrap_eth_post_request.py
hightop_sdk/models/api_actions_broadcast_post200_response.py
hightop_sdk/models/api_actions_broadcast_post_request.py
hightop_sdk-0.1.1.dist-info/METADATA
hightop_sdk-0.1.1.dist-info/WHEEL
hightop_sdk-0.1.1.dist-info/top_level.txt
hightop_sdk-0.1.1.dist-info/RECORD
